ImpSort/__init__.py
ImpSort/exceptions.py
ImpSort/imp_sort.py
ImpSort/logs.py
ImpSort/meta.py
ImpSort/version.py
ImpSort/algorithms/__init__.py
ImpSort/algorithms/bogo.py
ImpSort/algorithms/common.py
ImpSort/algorithms/rand_swap.py
ImpSort/algorithms/recompile.py
ImpSort/algorithms/stalin.py
ImpSort-0.0.2.dist-info/LICENSE
ImpSort-0.0.2.dist-info/METADATA
ImpSort-0.0.2.dist-info/WHEEL
ImpSort-0.0.2.dist-info/top_level.txt
ImpSort-0.0.2.dist-info/RECORD
