Metadata-Version: 2.1
Name: ImpSort
Version: 0.0.2
Summary: A python library for interacting with some very terrible sorting algorithms
Home-page: http://github.com/thedeltaflyer/ImpSort
Author: David Khudaverdyan
Author-email: khudaverdyan.david@gmail.com
License: MIT
Keywords: sorting bogo rand_swap
Platform: UNKNOWN
Classifier: Intended Audience :: Developers
Classifier: Topic :: Utilities
Classifier: License :: OSI Approved :: MIT License
Classifier: Natural Language :: English
Classifier: Operating System :: OS Independent
Classifier: Programming Language :: Python :: 3
Classifier: Programming Language :: Python :: 3.6
Classifier: Programming Language :: Python :: 3.7
Classifier: Programming Language :: Python :: 3.8
Provides-Extra: test
Requires-Dist: coverage ; extra == 'test'
Requires-Dist: pytest ; extra == 'test'
Requires-Dist: pytest-cov ; extra == 'test'
